README.rst
setup.cfg
setup.py
leenvs/__init__.py
logentries_envs.egg-info/PKG-INFO
logentries_envs.egg-info/SOURCES.txt
logentries_envs.egg-info/dependency_links.txt
logentries_envs.egg-info/requires.txt
logentries_envs.egg-info/top_level.txt