Metadata-Version: 1.0
Name: logentries-envs
Version: 0.0.4
Summary: Logentries Handler to get Token from environment variable.
Home-page: https://github.com/debonzi/logentries-envs
Author: Daniel Debonzi
Author-email: debonzi@gmail.com
License: UNKNOWN
Platform: UNKNOWN
